haip/__init__.py
haip-0.1.1.dist-info/LICENSE
haip-0.1.1.dist-info/METADATA
haip-0.1.1.dist-info/WHEEL
haip-0.1.1.dist-info/top_level.txt
haip-0.1.1.dist-info/RECORD
