Metadata-Version: 2.1
Name: haip
Version: 0.1.1
Summary: The root element of the haip namespace.
Home-page: https://github.com/haipdev/haip
Author: Reinhard Hainz
Author-email: reinhard.hainz@gmail.com
License: UNKNOWN
Platform: UNKNOWN
Classifier: Programming Language :: Python :: 3
Classifier: License :: OSI Approved :: MIT License
Classifier: Operating System :: OS Independent
